[
  {
    "id": 1,
    "title": "Personal Site",
    "slug": "/projects/personal-site",
    "description": "lorem ipsum",
    "githbLink": "",
    "siteLink": "",
    "label": "React, Gatsby, SCSS, styled-components"
  },
  {
    "id": 2,
    "title": "Automation",
    "slug": "/projects/automation",
    "description": "lorem ipsum",
    "githbLink": "",
    "siteLink": "",
    "label": ""
  },
  {
    "id": 3,
    "title": "Cocktail Recipe App",
    "slug": "/projects/drink-app",
    "description": "lorem ipsum",
    "githbLink": "",
    "siteLink": "",
    "label": "React Hooks, SASS"
  },
  {
    "id": 4,
    "title": "Quotes App",
    "slug": "/projects/quote-generator",
    "description": "lorem ipsum",
    "githbLink": "",
    "siteLink": "",
    "label": ""
  },
  {
    "id": 4,
    "title": "Form Validator",
    "slug": "/projects/form-validator",
    "description": "lorem ipsum",
    "githbLink": "",
    "siteLink": "",
    "label": ""
  }
]
